sud/__init__.py
sud/__main__.py
sud/cli.py
sud/config.py
sud/constants.py
sud/exceptions.py
sud/prompt.py
sud/updater.py
sud-0.3.0.dist-info/LICENSE
sud-0.3.0.dist-info/METADATA
sud-0.3.0.dist-info/WHEEL
sud-0.3.0.dist-info/entry_points.txt
sud-0.3.0.dist-info/RECORD
