Metadata-Version: 2.1
Name: sud
Version: 0.3.0
Summary: Scaleway Update DNS
Home-page: https://github.com/ffaraone/sud
License: Apache-2.0
Keywords: sud,scaleway,dns,dynamic,dynamicdns
Author: Francesco Faraone
Requires-Python: >=3.10,<4
Classifier: Development Status :: 4 - Beta
Classifier: Environment :: Console
Classifier: License :: OSI Approved :: Apache Software License
Classifier: Operating System :: OS Independent
Classifier: Programming Language :: Python :: 3
Classifier: Programming Language :: Python :: 3.10
Classifier: Programming Language :: Python :: 3.11
Classifier: Programming Language :: Python :: 3.12
Classifier: Topic :: Internet :: Name Service (DNS)
Classifier: Topic :: System :: Networking
Classifier: Topic :: Utilities
Requires-Dist: humanize (>=4.9.0,<5.0.0)
Requires-Dist: python-telegram-bot (>=20.8,<21.0)
Requires-Dist: pyyaml (>=6.0.1,<7.0.0)
Requires-Dist: requests (>=2.31.0,<3.0.0)
Requires-Dist: rich (>=13.7.0,<14.0.0)
Requires-Dist: typer[all] (>=0.9.0,<0.10.0)
Project-URL: Documentation, https://github.com/ffaraone/sud
Project-URL: Repository, https://github.com/ffaraone/sud
